mistyPy/EventFilters.py
mistyPy/Events.py
mistyPy/GenerateRobot.py
mistyPy/Robot.py
mistyPy/RobotCommands.py
mistyPy/__init__.py
Misty_SDK-0.1.dist-info/LICENSE
Misty_SDK-0.1.dist-info/METADATA
Misty_SDK-0.1.dist-info/WHEEL
Misty_SDK-0.1.dist-info/top_level.txt
Misty_SDK-0.1.dist-info/RECORD
